{
   Date: "2019-10-01",
   Time: "12:10:45",
   Stock: {
      "1 open":  225.4800,
      "2 high":  225.4800,
      "3 low":  225.4800,
      "4 close":  225.4800,
      "5 volume":  0
   }
}
{
   Date: "2019-10-01",
   Time: "11:30:00",
   Stock: {
      "1 open":  227.6500,
      "2 high":  227.6500,
      "3 low":  225.4350,
      "4 close":  225.6200,
      "5 volume":  2780316
   }
}
{
   Date: "2019-10-01",
   Time: "10:30:00",
   Stock: {
      "1 open":  226.7491,
      "2 high":  227.8581,
      "3 low":  226.2265,
      "4 close":  227.6491,
      "5 volume":  4840940
   }
}
{
   Date: "2019-10-01",
   Time: "09:30:00",
   Stock: {
      "1 open":  225.0200,
      "2 high":  228.2200,
      "3 low":  224.9600,
      "4 close":  226.7554,
      "5 volume":  12355302
   }
}
{
   Date: "2019-09-30",
   Time: "15:30:00",
   Stock: {
      "1 open":  224.0884,
      "2 high":  224.3400,
      "3 low":  223.7495,
      "4 close":  223.9884,
      "5 volume":  3147178
   }
}
{
   Date: "2019-09-30",
   Time: "14:30:00",
   Stock: {
      "1 open":  224.0344,
      "2 high":  224.5666,
      "3 low":  223.9961,
      "4 close":  224.0844,
      "5 volume":  2242211
   }
}
{
   Date: "2019-09-30",
   Time: "13:30:00",
   Stock: {
      "1 open":  223.9959,
      "2 high":  224.5774,
      "3 low":  223.7166,
      "4 close":  224.0160,
      "5 volume":  2129140
   }
}
{
   Date: "2019-09-30",
   Time: "12:30:00",
   Stock: {
      "1 open":  223.9700,
      "2 high":  224.5800,
      "3 low":  223.8200,
      "4 close":  223.9700,
      "5 volume":  2671782
   }
}
{
   Date: "2019-09-30",
   Time: "11:30:00",
   Stock: {
      "1 open":  223.2371,
      "2 high":  224.2197,
      "3 low":  223.1987,
      "4 close":  223.9771,
      "5 volume":  2823810
   }
}
{
   Date: "2019-09-30",
   Time: "10:30:00",
   Stock: {
      "1 open":  221.8189,
      "2 high":  223.4539,
      "3 low":  221.7723,
      "4 close":  223.2340,
      "5 volume":  3866426
   }
}
{
   Date: "2019-09-30",
   Time: "09:30:00",
   Stock: {
      "1 open":  220.9000,
      "2 high":  222.2300,
      "3 low":  220.7900,
      "4 close":  221.8050,
      "5 volume":  6265713
   }
}
{
   Date: "2019-09-27",
   Time: "15:30:00",
   Stock: {
      "1 open":  218.2700,
      "2 high":  219.1300,
      "3 low":  218.1796,
      "4 close":  218.8500,
      "5 volume":  2493686
   }
}
{
   Date: "2019-09-27",
   Time: "14:30:00",
   Stock: {
      "1 open":  218.1587,
      "2 high":  218.7994,
      "3 low":  217.4896,
      "4 close":  218.2988,
      "5 volume":  3996960
   }
}
{
   Date: "2019-09-27",
   Time: "13:30:00",
   Stock: {
      "1 open":  218.3571,
      "2 high":  219.0305,
      "3 low":  218.0295,
      "4 close":  218.1791,
      "5 volume":  2472926
   }
}
{
   Date: "2019-09-27",
   Time: "12:30:00",
   Stock: {
      "1 open":  219.1971,
      "2 high":  219.8537,
      "3 low":  218.3022,
      "4 close":  218.3471,
      "5 volume":  3399887
   }
}
{
   Date: "2019-09-27",
   Time: "11:30:00",
   Stock: {
      "1 open":  220.3636,
      "2 high":  220.6609,
      "3 low":  217.9886,
      "4 close":  219.2076,
      "5 volume":  4337360
   }
}
{
   Date: "2019-09-27",
   Time: "10:30:00",
   Stock: {
      "1 open":  220.0679,
      "2 high":  220.7249,
      "3 low":  219.6739,
      "4 close":  220.3779,
      "5 volume":  2484094
   }
}
{
   Date: "2019-09-27",
   Time: "09:30:00",
   Stock: {
      "1 open":  220.5443,
      "2 high":  221.0438,
      "3 low":  219.9630,
      "4 close":  220.0743,
      "5 volume":  4013418
   }
}
{
   Date: "2019-09-26",
   Time: "15:30:00",
   Stock: {
      "1 open":  220.4388,
      "2 high":  221.1517,
      "3 low":  219.6903,
      "4 close":  219.8988,
      "5 volume":  2108716
   }
}
{
   Date: "2019-09-26",
   Time: "14:30:00",
   Stock: {
      "1 open":  220.2592,
      "2 high":  220.8122,
      "3 low":  220.1916,
      "4 close":  220.4442,
      "5 volume":  1597442
   }
}
{
   Date: "2019-09-26",
   Time: "13:30:00",
   Stock: {
      "1 open":  219.8000,
      "2 high":  220.6900,
      "3 low":  219.7300,
      "4 close":  220.2400,
      "5 volume":  1486775
   }
}
{
   Date: "2019-09-26",
   Time: "12:30:00",
   Stock: {
      "1 open":  220.1912,
      "2 high":  220.2100,
      "3 low":  219.6500,
      "4 close":  219.8000,
      "5 volume":  1307844
   }
}
{
   Date: "2019-09-26",
   Time: "11:30:00",
   Stock: {
      "1 open":  219.5500,
      "2 high":  220.4300,
      "3 low":  219.5300,
      "4 close":  220.1893,
      "5 volume":  1985454
   }
}
{
   Date: "2019-09-26",
   Time: "10:30:00",
   Stock: {
      "1 open":  219.9582,
      "2 high":  221.0269,
      "3 low":  219.4083,
      "4 close":  219.5482,
      "5 volume":  3427286
   }
}
{
   Date: "2019-09-26",
   Time: "09:30:00",
   Stock: {
      "1 open":  219.6158,
      "2 high":  220.2391,
      "3 low":  219.1522,
      "4 close":  219.9658,
      "5 volume":  4429590
   }
}
{
   Date: "2019-09-25",
   Time: "15:30:00",
   Stock: {
      "1 open":  221.0200,
      "2 high":  221.5000,
      "3 low":  220.8000,
      "4 close":  220.9900,
      "5 volume":  2164532
   }
}
{
   Date: "2019-09-25",
   Time: "14:30:00",
   Stock: {
      "1 open":  220.2299,
      "2 high":  221.3852,
      "3 low":  220.2141,
      "4 close":  221.0271,
      "5 volume":  2191807
   }
}
{
   Date: "2019-09-25",
   Time: "13:30:00",
   Stock: {
      "1 open":  220.0400,
      "2 high":  220.9000,
      "3 low":  219.9000,
      "4 close":  220.2100,
      "5 volume":  1657900
   }
}
{
   Date: "2019-09-25",
   Time: "12:30:00",
   Stock: {
      "1 open":  220.6900,
      "2 high":  220.8400,
      "3 low":  219.8408,
      "4 close":  220.0000,
      "5 volume":  1636488
   }
}
{
   Date: "2019-09-25",
   Time: "11:30:00",
   Stock: {
      "1 open":  220.0082,
      "2 high":  221.1370,
      "3 low":  219.9659,
      "4 close":  220.7180,
      "5 volume":  2203114
   }
}
{
   Date: "2019-09-25",
   Time: "10:30:00",
   Stock: {
      "1 open":  219.1443,
      "2 high":  220.7236,
      "3 low":  219.0663,
      "4 close":  220.0237,
      "5 volume":  3784667
   }
}
{
   Date: "2019-09-25",
   Time: "09:30:00",
   Stock: {
      "1 open":  219.2900,
      "2 high":  219.6400,
      "3 low":  217.3400,
      "4 close":  219.1600,
      "5 volume":  6129718
   }
}
{
   Date: "2019-09-24",
   Time: "15:30:00",
   Stock: {
      "1 open":  217.9800,
      "2 high":  218.4200,
      "3 low":  217.5600,
      "4 close":  217.6900,
      "5 volume":  2918416
   }
}
{
   Date: "2019-09-24",
   Time: "14:30:00",
   Stock: {
      "1 open":  219.4336,
      "2 high":  219.6901,
      "3 low":  217.7674,
      "4 close":  217.9986,
      "5 volume":  3076080
   }
}
{
   Date: "2019-09-24",
   Time: "13:30:00",
   Stock: {
      "1 open":  217.2400,
      "2 high":  219.7000,
      "3 low":  217.1900,
      "4 close":  219.4200,
      "5 volume":  3295084
   }
}
{
   Date: "2019-09-24",
   Time: "12:30:00",
   Stock: {
      "1 open":  218.1400,
      "2 high":  218.5500,
      "3 low":  217.2111,
      "4 close":  217.2400,
      "5 volume":  3475775
   }
}
{
   Date: "2019-09-24",
   Time: "11:30:00",
   Stock: {
      "1 open":  220.3343,
      "2 high":  220.5434,
      "3 low":  217.7312,
      "4 close":  218.1783,
      "5 volume":  4275197
   }
}
{
   Date: "2019-09-24",
   Time: "10:30:00",
   Stock: {
      "1 open":  220.7158,
      "2 high":  221.3243,
      "3 low":  220.1331,
      "4 close":  220.3258,
      "5 volume":  3078818
   }
}
{
   Date: "2019-09-24",
   Time: "09:30:00",
   Stock: {
      "1 open":  221.0370,
      "2 high":  222.6501,
      "3 low":  220.3960,
      "4 close":  220.6871,
      "5 volume":  7776152
   }
}
{
   Date: "2019-09-23",
   Time: "15:30:00",
   Stock: {
      "1 open":  219.6000,
      "2 high":  219.8299,
      "3 low":  218.6000,
      "4 close":  218.6800,
      "5 volume":  2236666
   }
}
{
   Date: "2019-09-23",
   Time: "14:30:00",
   Stock: {
      "1 open":  219.4837,
      "2 high":  219.8400,
      "3 low":  219.3850,
      "4 close":  219.6100,
      "5 volume":  1272455
   }
}
{
   Date: "2019-09-23",
   Time: "13:30:00",
   Stock: {
      "1 open":  219.1763,
      "2 high":  219.6723,
      "3 low":  219.0244,
      "4 close":  219.4900,
      "5 volume":  1418464
   }
}
{
   Date: "2019-09-23",
   Time: "12:30:00",
   Stock: {
      "1 open":  219.0002,
      "2 high":  219.3725,
      "3 low":  218.7120,
      "4 close":  219.1843,
      "5 volume":  1179400
   }
}
{
   Date: "2019-09-23",
   Time: "11:30:00",
   Stock: {
      "1 open":  218.9645,
      "2 high":  219.4324,
      "3 low":  218.7818,
      "4 close":  219.0058,
      "5 volume":  2047488
   }
}
{
   Date: "2019-09-23",
   Time: "10:30:00",
   Stock: {
      "1 open":  218.1900,
      "2 high":  219.2200,
      "3 low":  218.0700,
      "4 close":  218.9500,
      "5 volume":  2851417
   }
}
{
   Date: "2019-09-23",
   Time: "09:30:00",
   Stock: {
      "1 open":  218.9588,
      "2 high":  219.7003,
      "3 low":  217.8585,
      "4 close":  218.1887,
      "5 volume":  5885090
   }
}
{
   Date: "2019-09-20",
   Time: "15:30:00",
   Stock: {
      "1 open":  218.7700,
      "2 high":  219.3438,
      "3 low":  217.6100,
      "4 close":  217.6900,
      "5 volume":  4852506
   }
}
{
   Date: "2019-09-20",
   Time: "14:30:00",
   Stock: {
      "1 open":  219.4770,
      "2 high":  219.9700,
      "3 low":  218.7100,
      "4 close":  218.7600,
      "5 volume":  2629453
   }
}
{
   Date: "2019-09-20",
   Time: "13:30:00",
   Stock: {
      "1 open":  218.9900,
      "2 high":  219.6900,
      "3 low":  217.6600,
      "4 close":  219.4700,
      "5 volume":  4525846
   }
}
{
   Date: "2019-09-20",
   Time: "12:30:00",
   Stock: {
      "1 open":  220.6656,
      "2 high":  220.8965,
      "3 low":  218.4541,
      "4 close":  218.9870,
      "5 volume":  4175509
   }
}
{
   Date: "2019-09-20",
   Time: "11:30:00",
   Stock: {
      "1 open":  221.8005,
      "2 high":  221.8100,
      "3 low":  220.5900,
      "4 close":  220.6400,
      "5 volume":  2356267
   }
}
{
   Date: "2019-09-20",
   Time: "10:30:00",
   Stock: {
      "1 open":  221.8300,
      "2 high":  222.4400,
      "3 low":  221.6700,
      "4 close":  221.8000,
      "5 volume":  3295233
   }
}
{
   Date: "2019-09-20",
   Time: "09:30:00",
   Stock: {
      "1 open":  221.3800,
      "2 high":  222.5600,
      "3 low":  221.3800,
      "4 close":  221.8100,
      "5 volume":  10364456
   }
}
{
   Date: "2019-09-19",
   Time: "15:30:00",
   Stock: {
      "1 open":  221.3900,
      "2 high":  221.6000,
      "3 low":  220.9400,
      "4 close":  220.9500,
      "5 volume":  2254188
   }
}
{
   Date: "2019-09-19",
   Time: "14:30:00",
   Stock: {
      "1 open":  221.3470,
      "2 high":  221.7173,
      "3 low":  220.9666,
      "4 close":  221.3970,
      "5 volume":  2180307
   }
}
{
   Date: "2019-09-19",
   Time: "13:30:00",
   Stock: {
      "1 open":  221.2089,
      "2 high":  221.9324,
      "3 low":  220.5811,
      "4 close":  221.3541,
      "5 volume":  2555507
   }
}
{
   Date: "2019-09-19",
   Time: "12:30:00",
   Stock: {
      "1 open":  221.0092,
      "2 high":  221.9133,
      "3 low":  220.9824,
      "4 close":  221.2092,
      "5 volume":  1874414
   }
}
{
   Date: "2019-09-19",
   Time: "11:30:00",
   Stock: {
      "1 open":  222.5450,
      "2 high":  223.0200,
      "3 low":  220.9600,
      "4 close":  221.0000,
      "5 volume":  2720665
   }
}
{
   Date: "2019-09-19",
   Time: "10:30:00",
   Stock: {
      "1 open":  222.9900,
      "2 high":  223.7600,
      "3 low":  222.4800,
      "4 close":  222.5400,
      "5 volume":  3080288
   }
}
{
   Date: "2019-09-19",
   Time: "09:30:00",
   Stock: {
      "1 open":  222.0600,
      "2 high":  223.2400,
      "3 low":  222.0500,
      "4 close":  222.9884,
      "5 volume":  5565133
   }
}
{
   Date: "2019-09-18",
   Time: "15:30:00",
   Stock: {
      "1 open":  222.0200,
      "2 high":  222.8500,
      "3 low":  221.9600,
      "4 close":  222.7700,
      "5 volume":  3465979
   }
}
{
   Date: "2019-09-18",
   Time: "14:30:00",
   Stock: {
      "1 open":  219.9188,
      "2 high":  222.4029,
      "3 low":  219.8604,
      "4 close":  222.0489,
      "5 volume":  4205215
   }
}
{
   Date: "2019-09-18",
   Time: "13:30:00",
   Stock: {
      "1 open":  220.8092,
      "2 high":  222.0434,
      "3 low":  219.6511,
      "4 close":  219.9010,
      "5 volume":  3820187
   }
}
{
   Date: "2019-09-18",
   Time: "12:30:00",
   Stock: {
      "1 open":  221.5700,
      "2 high":  221.6500,
      "3 low":  220.6400,
      "4 close":  220.7875,
      "5 volume":  1887681
   }
}
{
   Date: "2019-09-18",
   Time: "11:30:00",
   Stock: {
      "1 open":  221.9500,
      "2 high":  222.0900,
      "3 low":  221.3900,
      "4 close":  221.5700,
      "5 volume":  1457193
   }
}
{
   Date: "2019-09-18",
   Time: "10:30:00",
   Stock: {
      "1 open":  222.3200,
      "2 high":  222.5200,
      "3 low":  221.9200,
      "4 close":  221.9600,
      "5 volume":  2324793
   }
}
{
   Date: "2019-09-18",
   Time: "09:30:00",
   Stock: {
      "1 open":  221.0143,
      "2 high":  222.6151,
      "3 low":  220.8537,
      "4 close":  222.3194,
      "5 volume":  5852071
   }
}
{
   Date: "2019-09-17",
   Time: "15:30:00",
   Stock: {
      "1 open":  220.1600,
      "2 high":  220.8200,
      "3 low":  220.1500,
      "4 close":  220.6500,
      "5 volume":  1784928
   }
}
{
   Date: "2019-09-17",
   Time: "14:30:00",
   Stock: {
      "1 open":  219.9500,
      "2 high":  220.2200,
      "3 low":  219.8000,
      "4 close":  220.1600,
      "5 volume":  1509959
   }
}
{
   Date: "2019-09-17",
   Time: "13:30:00",
   Stock: {
      "1 open":  220.0900,
      "2 high":  220.3500,
      "3 low":  219.8500,
      "4 close":  219.9400,
      "5 volume":  1587954
   }
}
{
   Date: "2019-09-17",
   Time: "12:30:00",
   Stock: {
      "1 open":  219.9436,
      "2 high":  220.4507,
      "3 low":  219.7501,
      "4 close":  220.0936,
      "5 volume":  2106940
   }
}
{
   Date: "2019-09-17",
   Time: "11:30:00",
   Stock: {
      "1 open":  220.2529,
      "2 high":  220.6448,
      "3 low":  219.7640,
      "4 close":  219.9379,
      "5 volume":  1754587
   }
}
{
   Date: "2019-09-17",
   Time: "10:30:00",
   Stock: {
      "1 open":  219.5300,
      "2 high":  220.5900,
      "3 low":  219.5300,
      "4 close":  220.2400,
      "5 volume":  2594461
   }
}
{
   Date: "2019-09-17",
   Time: "09:30:00",
   Stock: {
      "1 open":  219.7098,
      "2 high":  220.8033,
      "3 low":  219.4224,
      "4 close":  219.5158,
      "5 volume":  4756817
   }
}
{
   Date: "2019-09-16",
   Time: "15:30:00",
   Stock: {
      "1 open":  219.6700,
      "2 high":  220.0700,
      "3 low":  219.5400,
      "4 close":  219.9100,
      "5 volume":  1568208
   }
}
{
   Date: "2019-09-16",
   Time: "14:30:00",
   Stock: {
      "1 open":  219.8200,
      "2 high":  219.9900,
      "3 low":  219.5601,
      "4 close":  219.6800,
      "5 volume":  1820127
   }
}
{
   Date: "2019-09-16",
   Time: "13:30:00",
   Stock: {
      "1 open":  219.4433,
      "2 high":  220.1000,
      "3 low":  219.4400,
      "4 close":  219.8200,
      "5 volume":  2250373
   }
}
{
   Date: "2019-09-16",
   Time: "12:30:00",
   Stock: {
      "1 open":  219.3179,
      "2 high":  219.6767,
      "3 low":  219.1135,
      "4 close":  219.4479,
      "5 volume":  1497013
   }
}
{
   Date: "2019-09-16",
   Time: "11:30:00",
   Stock: {
      "1 open":  219.9082,
      "2 high":  220.3363,
      "3 low":  219.1051,
      "4 close":  219.3217,
      "5 volume":  2615614
   }
}
{
   Date: "2019-09-16",
   Time: "10:30:00",
   Stock: {
      "1 open":  218.4043,
      "2 high":  220.2682,
      "3 low":  218.3617,
      "4 close":  219.9103,
      "5 volume":  3359289
   }
}
{
   Date: "2019-09-16",
   Time: "09:30:00",
   Stock: {
      "1 open":  218.4500,
      "2 high":  220.0200,
      "3 low":  217.7500,
      "4 close":  218.3900,
      "5 volume":  6211563
   }
}
{
   Date: "2019-09-13",
   Time: "15:30:00",
   Stock: {
      "1 open":  219.0479,
      "2 high":  219.4437,
      "3 low":  218.5729,
      "4 close":  218.8079,
      "5 volume":  3485513
   }
}
{
   Date: "2019-09-13",
   Time: "14:30:00",
   Stock: {
      "1 open":  218.7050,
      "2 high":  219.8100,
      "3 low":  218.5200,
      "4 close":  219.0500,
      "5 volume":  3732736
   }
}
{
   Date: "2019-09-13",
   Time: "13:30:00",
   Stock: {
      "1 open":  217.5143,
      "2 high":  219.8229,
      "3 low":  217.1908,
      "4 close":  218.7140,
      "5 volume":  6572185
   }
}
{
   Date: "2019-09-13",
   Time: "12:30:00",
   Stock: {
      "1 open":  217.8905,
      "2 high":  218.3013,
      "3 low":  217.2903,
      "4 close":  217.5157,
      "5 volume":  3604541
   }
}
{
   Date: "2019-09-13",
   Time: "11:30:00",
   Stock: {
      "1 open":  218.8100,
      "2 high":  219.0900,
      "3 low":  217.5800,
      "4 close":  217.8900,
      "5 volume":  4166242
   }
}
{
   Date: "2019-09-13",
   Time: "10:30:00",
   Stock: {
      "1 open":  219.3803,
      "2 high":  219.6953,
      "3 low":  218.5642,
      "4 close":  218.8270,
      "5 volume":  4589991
   }
}
{
   Date: "2019-09-13",
   Time: "09:30:00",
   Stock: {
      "1 open":  219.6292,
      "2 high":  220.9423,
      "3 low":  219.0305,
      "4 close":  219.3692,
      "5 volume":  11032845
   }
}
{
   Date: "2019-09-12",
   Time: "15:30:00",
   Stock: {
      "1 open":  224.5584,
      "2 high":  225.0807,
      "3 low":  223.0688,
      "4 close":  223.0983,
      "5 volume":  3306676
   }
}
{
   Date: "2019-09-12",
   Time: "14:30:00",
   Stock: {
      "1 open":  224.9200,
      "2 high":  225.3300,
      "3 low":  224.4200,
      "4 close":  224.5500,
      "5 volume":  2035273
   }
}
{
   Date: "2019-09-12",
   Time: "13:30:00",
   Stock: {
      "1 open":  225.1259,
      "2 high":  225.6284,
      "3 low":  224.8677,
      "4 close":  224.9259,
      "5 volume":  1767137
   }
}
{
   Date: "2019-09-12",
   Time: "12:30:00",
   Stock: {
      "1 open":  225.2600,
      "2 high":  225.8800,
      "3 low":  225.0000,
      "4 close":  225.1100,
      "5 volume":  2168471
   }
}
{
   Date: "2019-09-12",
   Time: "11:30:00",
   Stock: {
      "1 open":  225.5172,
      "2 high":  226.0816,
      "3 low":  225.1507,
      "4 close":  225.2572,
      "5 volume":  2850778
   }
}
{
   Date: "2019-09-12",
   Time: "10:30:00",
   Stock: {
      "1 open":  225.9291,
      "2 high":  226.2165,
      "3 low":  224.0444,
      "4 close":  225.4990,
      "5 volume":  4526886
   }
}
{
   Date: "2019-09-12",
   Time: "09:30:00",
   Stock: {
      "1 open":  224.7573,
      "2 high":  226.6203,
      "3 low":  223.2670,
      "4 close":  225.9087,
      "5 volume":  11545740
   }
}
{
   Date: "2019-09-11",
   Time: "15:30:00",
   Stock: {
      "1 open":  222.5050,
      "2 high":  223.5900,
      "3 low":  222.4900,
      "4 close":  223.3900,
      "5 volume":  4103290
   }
}
{
   Date: "2019-09-11",
   Time: "14:30:00",
   Stock: {
      "1 open":  222.1858,
      "2 high":  222.8958,
      "3 low":  221.9348,
      "4 close":  222.5059,
      "5 volume":  3243517
   }
}
{
   Date: "2019-09-11",
   Time: "13:30:00",
   Stock: {
      "1 open":  222.4500,
      "2 high":  222.7300,
      "3 low":  222.0600,
      "4 close":  222.1800,
      "5 volume":  3243503
   }
}
{
   Date: "2019-09-11",
   Time: "12:30:00",
   Stock: {
      "1 open":  222.3420,
      "2 high":  223.1600,
      "3 low":  222.3250,
      "4 close":  222.4600,
      "5 volume":  4031377
   }
}
{
   Date: "2019-09-11",
   Time: "11:30:00",
   Stock: {
      "1 open":  220.8600,
      "2 high":  222.9500,
      "3 low":  220.8600,
      "4 close":  222.3386,
      "5 volume":  6638912
   }
}
